fiddler_strandsagents/VERSION
fiddler_strandsagents/__init__.py
fiddler_strandsagents/attributes.py
fiddler_strandsagents/constants.py
fiddler_strandsagents/hooks.py
fiddler_strandsagents/instrumentation.py
fiddler_strandsagents/span_processor.py
fiddler_strands-0.4.0.dist-info/METADATA
fiddler_strands-0.4.0.dist-info/WHEEL
fiddler_strands-0.4.0.dist-info/licenses/LICENSE
fiddler_strands-0.4.0.dist-info/RECORD
