Metadata-Version: 2.4
Name: fiddler-strands
Version: 0.4.0
Summary: Fiddler SDK for Strands Agent instrumentation with OpenTelemetry
Project-URL: Homepage, https://github.com/fiddler-labs/fiddler-strands-sdk
Project-URL: Repository, https://github.com/fiddler-labs/fiddler-strands-sdk
Project-URL: Documentation, https://docs.fiddler.ai/strands-sdk
Project-URL: Issues, https://github.com/fiddler-labs/fiddler-strands-sdk/issues
Author-email: Fiddler AI <support@fiddler.ai>
License: Apache-2.0
License-File: LICENSE
Classifier: Development Status :: 3 - Alpha
Classifier: Intended Audience :: Developers
Classifier: License :: OSI Approved :: Apache Software License
Classifier: Programming Language :: Python :: 3
Classifier: Programming Language :: Python :: 3.10
Classifier: Programming Language :: Python :: 3.11
Classifier: Programming Language :: Python :: 3.12
Classifier: Programming Language :: Python :: 3.13
Requires-Python: >=3.10
Requires-Dist: opentelemetry-api>=1.20.0
Requires-Dist: opentelemetry-exporter-otlp>=1.20.0
Requires-Dist: opentelemetry-instrumentation>=0.41b0
Requires-Dist: opentelemetry-sdk>=1.20.0
Requires-Dist: strands-agents>=1.10.0
Provides-Extra: dev
Requires-Dist: bandit>=1.8.5; extra == 'dev'
Requires-Dist: black>=25.1.0; extra == 'dev'
Requires-Dist: flake8>=7.2.0; extra == 'dev'
Requires-Dist: ipython>=8.12.3; extra == 'dev'
Requires-Dist: isort>=6.0; extra == 'dev'
Requires-Dist: mypy>=1.16.1; extra == 'dev'
Requires-Dist: nox>=2025.5.1; extra == 'dev'
Requires-Dist: pre-commit>=4.2.0; extra == 'dev'
Requires-Dist: pylint>=3.3.7; extra == 'dev'
Requires-Dist: pytest-asyncio>=0.24.0; extra == 'dev'
Requires-Dist: pytest-cov>=6.1.1; extra == 'dev'
Requires-Dist: pytest>=8.3.5; extra == 'dev'
Requires-Dist: ruff>=0.13.3; extra == 'dev'
Requires-Dist: strands-agents[openai]==1.12.0; extra == 'dev'
Requires-Dist: tomli==2.2.1; extra == 'dev'
Provides-Extra: examples
Requires-Dist: openai>=1.0.0; extra == 'examples'
Requires-Dist: python-dotenv>=1.0.0; extra == 'examples'
Requires-Dist: strands-agents-tools>=0.2.0; extra == 'examples'
